girder/__init__.py
girder/asgi.py
girder/constants.py
girder/events.py
girder/exceptions.py
girder/notification.py
girder/plugin.py
girder/settings.py
girder/tasks.py
girder/worker_plugin.py
girder/wsgi.py
girder/api/__init__.py
girder/api/access.py
girder/api/api_docs.mako
girder/api/api_main.py
girder/api/describe.py
girder/api/docs.py
girder/api/filter_logging.py
girder/api/rest.py
girder/api/sftp.py
girder/api/v1/__init__.py
girder/api/v1/api_key.py
girder/api/v1/assetstore.py
girder/api/v1/collection.py
girder/api/v1/file.py
girder/api/v1/folder.py
girder/api/v1/group.py
girder/api/v1/item.py
girder/api/v1/resource.py
girder/api/v1/system.py
girder/api/v1/token.py
girder/api/v1/user.py
girder/cli/__init__.py
girder/cli/mount.py
girder/cli/serve.py
girder/cli/sftpd.py
girder/cli/shell.py
girder/mail_templates/_footer.mako
girder/mail_templates/_header.mako
girder/mail_templates/accountApproval.mako
girder/mail_templates/accountApproved.mako
girder/mail_templates/emailVerification.mako
girder/mail_templates/groupInvite.mako
girder/mail_templates/temporaryAccess.mako
girder/models/__init__.py
girder/models/api_key.py
girder/models/assetstore.py
girder/models/collection.py
girder/models/file.py
girder/models/folder.py
girder/models/group.py
girder/models/item.py
girder/models/model_base.py
girder/models/setting.py
girder/models/token.py
girder/models/upload.py
girder/models/user.py
girder/utility/__init__.py
girder/utility/_cache.py
girder/utility/_hash_state.py
girder/utility/abstract_assetstore_adapter.py
girder/utility/acl_mixin.py
girder/utility/assetstore_utilities.py
girder/utility/config.py
girder/utility/error.mako
girder/utility/filesystem_assetstore_adapter.py
girder/utility/mail_utils.py
girder/utility/model_importer.py
girder/utility/path.py
girder/utility/progress.py
girder/utility/s3_assetstore_adapter.py
girder/utility/search.py
girder/utility/server.py
girder/utility/setting_utilities.py
girder/utility/system.py
girder/utility/webroot.py
girder-5.0.0a14.dev27.dist-info/licenses/LICENSE
girder-5.0.0a14.dev27.dist-info/METADATA
girder-5.0.0a14.dev27.dist-info/WHEEL
girder-5.0.0a14.dev27.dist-info/entry_points.txt
girder-5.0.0a14.dev27.dist-info/top_level.txt
girder-5.0.0a14.dev27.dist-info/RECORD
