Metadata-Version: 2.4
Name: girder
Version: 5.0.0a14.dev27
Summary: Web-based data management platform
Home-page: https://girder.readthedocs.org
Author: Kitware, Inc.
Author-email: kitware@kitware.com
License: Apache 2.0
Classifier: Development Status :: 5 - Production/Stable
Classifier: Environment :: Web Environment
Classifier: Operating System :: OS Independent
Classifier: Programming Language :: Python
Classifier: Programming Language :: Python :: 3
Requires-Python: >=3.10
License-File: LICENSE
Requires-Dist: bcrypt
Requires-Dist: boto3
Requires-Dist: botocore
Requires-Dist: cheroot!=11.0.0,!=11.1.1
Requires-Dist: CherryPy
Requires-Dist: click
Requires-Dist: click-plugins
Requires-Dist: dogpile.cache<1.4
Requires-Dist: filelock
Requires-Dist: girder-worker>=5.0.0a5
Requires-Dist: jsonschema
Requires-Dist: Mako
Requires-Dist: packaging
Requires-Dist: pymongo>=4
Requires-Dist: PyYAML
Requires-Dist: psutil
Requires-Dist: pyOpenSSL
Requires-Dist: pyotp
Requires-Dist: python-dateutil
Requires-Dist: pytz
Requires-Dist: redis
Requires-Dist: requests
Requires-Dist: starlette
Requires-Dist: uvicorn
Requires-Dist: websockets
Provides-Extra: sftp
Requires-Dist: paramiko; extra == "sftp"
Provides-Extra: mount
Requires-Dist: cachetools; extra == "mount"
Requires-Dist: diskcache; extra == "mount"
Requires-Dist: fusepy>=3.0; extra == "mount"
Dynamic: author
Dynamic: author-email
Dynamic: classifier
Dynamic: description
Dynamic: home-page
Dynamic: license
Dynamic: license-file
Dynamic: provides-extra
Dynamic: requires-dist
Dynamic: requires-python
Dynamic: summary
